mignonFramework/__init__.py
mignonFramework/utils/BaseStateTracker.py
mignonFramework/utils/GenericProcessor.py
mignonFramework/utils/Logger.py
mignonFramework/utils/Louru_Plus.py
mignonFramework/utils/MoveStateTracker.py
mignonFramework/utils/ProcessFile.py
mignonFramework/utils/Queues.py
mignonFramework/utils/SQLiteStateTracker.py
mignonFramework/utils/__init__.py
mignonFramework/utils/dataBaseTransfer.py
mignonFramework/utils/eazy_mode_app.py
mignonFramework/utils/mignonFramework_starter.py
mignonFramework/utils/BackendAugmentation/RequestsMapping.py
mignonFramework/utils/BackendAugmentation/__init__.py
mignonFramework/utils/BackendAugmentation/web.py
mignonFramework/utils/config/ConfigReader.py
mignonFramework/utils/config/JsonlConfigReader.py
mignonFramework/utils/config/SQLiteTracker.py
mignonFramework/utils/config/__init__.py
mignonFramework/utils/execJS/MicroserviceByNodeJS.py
mignonFramework/utils/execJS/__init__.py
mignonFramework/utils/execJS/execJSTo.py
mignonFramework/utils/reader/BaseReader.py
mignonFramework/utils/reader/JSONLineReader.py
mignonFramework/utils/reader/XlsxReader.py
mignonFramework/utils/reader/__init__.py
mignonFramework/utils/starterUtil/__init__.py
mignonFramework/utils/starterUtil/app_runner.py
mignonFramework/utils/starterUtil/code_generator.py
mignonFramework/utils/starterUtil/views.py
mignonFramework/utils/starterUtil/__pycache__/__init__.cpython-311.pyc
mignonFramework/utils/starterUtil/__pycache__/app_runner.cpython-311.pyc
mignonFramework/utils/starterUtil/__pycache__/code_generator.cpython-311.pyc
mignonFramework/utils/starterUtil/__pycache__/views.cpython-311.pyc
mignonFramework/utils/starterUtil/static/css/aurora_button.css
mignonFramework/utils/starterUtil/static/css/landing.css
mignonFramework/utils/starterUtil/static/css/modules.css
mignonFramework/utils/starterUtil/static/css/shared.css
mignonFramework/utils/starterUtil/static/ico/favicon.ico
mignonFramework/utils/starterUtil/static/js/JSONcrypto.jsx
mignonframework-0.5.5.0.dist-info/licenses/LICENSE
mignonframework-0.5.5.0.dist-info/METADATA
mignonframework-0.5.5.0.dist-info/WHEEL
mignonframework-0.5.5.0.dist-info/top_level.txt
mignonframework-0.5.5.0.dist-info/RECORD
