Metadata-Version: 2.4
Name: mignonFramework
Version: 0.5.5.0
Summary: 一个为爬虫设计的强大Python工具集
Home-page: https://github.com/RexMignon/MignonFramework
Author: Mignon Rex
Author-email: rexdpbm@gmail.com
Classifier: Development Status :: 3 - Alpha
Classifier: License :: OSI Approved :: MIT License
Classifier: Operating System :: OS Independent
Classifier: Programming Language :: Python :: 3
Classifier: Programming Language :: Python :: 3.8
Classifier: Programming Language :: Python :: 3.9
Classifier: Programming Language :: Python :: 3.10
Classifier: Programming Language :: Python :: 3.11
Classifier: Programming Language :: Python :: 3.12
Classifier: Programming Language :: Python :: 3.13
Classifier: Intended Audience :: Developers
Classifier: Topic :: Software Development :: Libraries :: Python Modules
Classifier: Topic :: Internet :: WWW/HTTP
Classifier: Topic :: System :: Networking
Requires-Python: >=3.8
License-File: LICENSE
Requires-Dist: openpyxl
Requires-Dist: requests
Requires-Dist: pymysql
Requires-Dist: PyExecJS
Requires-Dist: aiofiles
Requires-Dist: tqdm
Requires-Dist: Flask
Requires-Dist: curl_cffi
Requires-Dist: loguru
Dynamic: author
Dynamic: author-email
Dynamic: classifier
Dynamic: description
Dynamic: description-content-type
Dynamic: home-page
Dynamic: license-file
Dynamic: requires-dist
Dynamic: requires-python
Dynamic: summary
